{"country":"Brazil","city":[{"city":"Mogi Guacu","outbreak":[{"disease":"Dengue Fever"}]}]}
{"country":"France","city":[{"city":"Paris","outbreak":[{"disease":"Dengue Fever"}]}]}
{"country":"Mozambique","city":[{"city":"Maputo","outbreak":[{"disease":"Malaria"}]}]}
{"country":"Zimbabwe","city":[{"city":"Manicaland","outbreak":[{"disease":"Malaria"}]}]}
{"country":"Tanzania","city":[{"city":"Dodoma","outbreak":[{"disease":"Dengue Fever"}]}]}
{"country":"Indonesia","city":[{"city":"Jakarta","outbreak":[{"disease":"Malaria"}]}]}
